mindx/__init__.py
mindx/core.py
openmindx-0.1.0.dist-info/licenses/LICENSE
openmindx-0.1.0.dist-info/METADATA
openmindx-0.1.0.dist-info/WHEEL
openmindx-0.1.0.dist-info/top_level.txt
openmindx-0.1.0.dist-info/RECORD
