Metadata-Version: 2.4
Name: openmindx
Version: 0.1.0
Summary: 一个确定性时延的图像生成大模型
Home-page: https://github.com/yourusername/openmindx
Author: wawei
Author-email: wawei@wawei.com
Classifier: Programming Language :: Python :: 3
Classifier: License :: OSI Approved :: MIT License
Classifier: Operating System :: OS Independent
Requires-Python: >=3.6
License-File: LICENSE
Dynamic: author
Dynamic: author-email
Dynamic: classifier
Dynamic: description
Dynamic: description-content-type
Dynamic: home-page
Dynamic: license-file
Dynamic: requires-python
Dynamic: summary
